[
  {
    "Who": "Laura Griffin",
    "Word Count": 111,
    "Quote": "You never know who's going to walk through your door or what they are going to want. We recently had a customer",
    "Start": 0,
    "End": "0:12"
  },
  {
    "Who": "Laura Griffin",
    "Word Count": 103,
    "Quote": "come in that was an older woman and she had a sketch that she wanted us to blow up for her. So we did. ",
    "Start": "0:12",
    "End": "0:18"
  },
  {
    "Who": "Sandy Scandrett",
    "Word Count": 92,
    "Quote": "we can do just about anything here. Small business, printing, shipping, packaging, shredding",
    "Start": "0:18",
    "End": "0:25"
  },
  {
    "Who": "Hamo Gharibian",
    "Word Count": 124,
    "Quote": "I do not say no to any project. If the customer comes through the door even if I do not know how to do it, I say yes to it. ",
    "Start": "0:25",
    "End": "0:34"
  },
  {
    "Who": "Greg Murray",
    "Word Count": 89,
    "Quote": "the interesting thing about UPS Store is that when the customer walks to the door there's",
    "Start": "0:34",
    "End": "0:40"
  },
  {
    "Who": "Greg Murray",
    "Word Count": 99,
    "Quote": " an extremely high probability that they're coming there to do something that is important to them.",
    "Start": "0:40",
    "End": "0:44"
  },
  {
    "Who": "Laura Griffin",
    "Word Count": 91,
    "Quote": "she came back a few weeks later with any enormous painting to ship. And it was the painting",
    "Start": "0:44",
    "End": "0:50"
  },
  {
    "Who": "Laura Griffin",
    "Word Count": 78,
    "Quote": "that she had repainted from the sketch we had blown up. So it was cool to see ",
    "Start": "0:50",
    "End": "0:53"
  },
  {
    "Who": "Laura Griffin",
    "Word Count": 57,
    "Quote": "the final finished product and we shipped it off for her ",
    "Start": "0:53",
    "End": "0:59"
  },
  {
    "Who": "Sandy Scandrett",
    "Word Count": 112,
    "Quote": "We, we do a really good job when it comes to packaging up items for customers. We treat it as if it was our own.",
    "Start": "0:59",
    "End": "1:06"
  },
  {
    "Who": "Matthew Wood",
    "Word Count": 92,
    "Quote": "When they bring an idea on a sheet of paper and then we can sit down and design and make the",
    "Start": "1:06",
    "End": "1:13"
  },
  {
    "Who": "Matthew Wood",
    "Word Count": 93,
    "Quote": "product for them and print it out and see the smile on their face brings satisfaction to me. ",
    "Start": "1:13",
    "End": "1:17"
  },
  {
    "Who": "Joy Batchelor",
    "Word Count": 84,
    "Quote": "I worked on the local restaurant for six months and their printer finally broke and ",
    "Start": "1:17",
    "End": "1:24"
  },
  {
    "Who": "Joy Batchelor",
    "Word Count": 105,
    "Quote": "they were printing their menus out. And they came to me just so they could use their own paper to print. ",
    "Start": "1:24",
    "End": "1:30"
  },
  {
    "Who": "Joy Batchelor",
    "Word Count": 94,
    "Quote": "And I quoted them on their exact paper and found out that I can actually get them their menus ",
    "Start": "1:30",
    "End": "1:36"
  },
  {
    "Who": "Joy Batchelor",
    "Word Count": 78,
    "Quote": "for a $1.75 cheaper than what they were doing right now on their own printer. ",
    "Start": "1:36",
    "End": "1:41"
  },
  {
    "Who": "Joy Batchelor",
    "Word Count": 75,
    "Quote": "And they were so excited that they can't wait to print with me forever now.",
    "Start": "1:41",
    "End": "1:46"
  },
  {
    "Who": "Greg Murray",
    "Word Count": 95,
    "Quote": "First thing is customer service. The other stuff is a positive side effect coming out of that. ",
    "Start": "1:46",
    "End": "1:51"
  },
  {
    "Who": "Matthew Wood",
    "Word Count": 78,
    "Quote": "A print customer came into this store several years ago and asked us to serve ",
    "Start": "1:51",
    "End": "1:58"
  },
  {
    "Who": "Matthew Wood",
    "Word Count": 78,
    "Quote": "as a fulfilment center for them where we actually print and produce textbooks ",
    "Start": "1:58",
    "End": "2:06"
  },
  {
    "Who": "Matthew Wood",
    "Word Count": 98,
    "Quote": "and then ship them out individually to um, their customers all across the US and internationally. ",
    "Start": "2:06",
    "End": "2:12"
  },
  {
    "Who": "Matthew Wood",
    "Word Count": 104,
    "Quote": "That was satisfying for me because we are able to be the one stop solution for that particular customer.",
    "Start": "2:12",
    "End": "2:20"
  },
  {
    "Who": "Joy Batchelor",
    "Word Count": 107,
    "Quote": "What makes it worthwhile at the end of the day is the customers. The customers treat us like we're family. ",
    "Start": "2:20",
    "End": "2:28"
  },
  {
    "Who": "",
    "Word Count": "",
    "Quote": "",
    "Start": "",
    "End": ""
  },
  {
    "Who": "",
    "Word Count": "",
    "Quote": "",
    "Start": "",
    "End": ""
  },
  {
    "Who": "",
    "Word Count": "",
    "Quote": "",
    "Start": "",
    "End": ""
  },
  {
    "Who": "",
    "Word Count": "",
    "Quote": "",
    "Start": "",
    "End": ""
  },
  {
    "Who": "",
    "Word Count": "",
    "Quote": "  ",
    "Start": "",
    "End": ""
  }
]