[
  {
    "Who": "Greg Murray",
    "Word Count": 84,
    "Quote": "So for my wife and I ah, we had the three criteria. It needed to be interesting and ",
    "Start": 0,
    "End": "0:06"
  },
  {
    "Who": "Greg Murray",
    "Word Count": 79,
    "Quote": "challenging, it had to be meaningful, and it had to have the opportunity to be ",
    "Start": "0:06",
    "End": "0:10"
  },
  {
    "Who": "Greg Murray",
    "Word Count": 72,
    "Quote": "financially rewarding and we have not been disappointed in any of that. ",
    "Start": "0:10",
    "End": "0:14"
  },
  {
    "Who": "Laura Griffin",
    "Word Count": 116,
    "Quote": "Every day um, there's something new that happens with our customers, with our employees. Um, it's a great challenge.",
    "Start": "0:14",
    "End": "0:21"
  },
  {
    "Who": "Sandy Scandrett",
    "Word Count": 110,
    "Quote": "For me, that means balance. For me, that means better financial opportunities. I love going iin every morning.",
    "Start": "0:21",
    "End": "0:26"
  },
  {
    "Who": "Hamo Gharibian",
    "Word Count": 33,
    "Quote": "Everyday you learn something new.",
    "Start": "0:25",
    "End": "0:28"
  },
  {
    "Who": "Greg Gagnon",
    "Word Count": 98,
    "Quote": "I think the best part about owning your own business is being able to make some of your own rules.",
    "Start": "0:28",
    "End": "0:32"
  },
  {
    "Who": "Greg Murray",
    "Word Count": 95,
    "Quote": "We hire the types of people we want to hire. We motivate them the way we want to motivate them.",
    "Start": "0:32",
    "End": "0:37"
  },
  {
    "Who": "Naresh Bhatt",
    "Word Count": 59,
    "Quote": "So, I can manage my own schedule. I can manage my own time.",
    "Start": "0:37",
    "End": "0:40"
  },
  {
    "Who": "Matthew Wood",
    "Word Count": 65,
    "Quote": "It's allowed me to dream bigger um, and think outside of the box.",
    "Start": "0:40",
    "End": "0:45"
  },
  {
    "Who": "Joy Batchelor",
    "Word Count": 107,
    "Quote": "What makes it worthwhile at the end of the day is the customers. The customers treat us like we're family. ",
    "Start": "0:45",
    "End": "0:52"
  },
  {
    "Who": "Greg Murray",
    "Word Count": 98,
    "Quote": "The interesting thing about The UPS Store is that when the customer walks through the door there's",
    "Start": "0:52",
    "End": "0:57"
  },
  {
    "Who": "Greg Murray",
    "Word Count": 97,
    "Quote": "an extremely high probability that they're coming there to do something that's important to them.",
    "Start": "0:57",
    "End": "1:02"
  },
  {
    "Who": "Matthew Wood",
    "Word Count": 91,
    "Quote": "When they bring in an idea on a sheet of paper and then we can sit down and design and make",
    "Start": "1:02",
    "End": "1:07"
  },
  {
    "Who": "Matthew Wood",
    "Word Count": 98,
    "Quote": "that product for them and print it out and see the smile on their face brings satisfaction to me. ",
    "Start": "1:07",
    "End": "1:13"
  },
  {
    "Who": "Sandy Scandrett",
    "Word Count": 85,
    "Quote": "Owning my own um business, my own franchise has, uh improved every aspect of my life.",
    "Start": "1:13",
    "End": "1:18"
  },
  {
    "Who": "Greg Gagnon",
    "Word Count": 78,
    "Quote": "For me, that means balance. For me, that means better financial opportunities.",
    "Start": "1:18",
    "End": "1:23"
  },
  {
    "Who": "Laura Griffin",
    "Word Count": 41,
    "Quote": "We have a community of other franchisees.",
    "Start": "1:23",
    "End": "1:26"
  },
  {
    "Who": "Jim George",
    "Word Count": 84,
    "Quote": "Everybody loves to help everybody else and you're, you're really part of a-a family.",
    "Start": "1:26",
    "End": "1:31"
  },
  {
    "Who": "Naresh Bhatt",
    "Word Count": 81,
    "Quote": "And in addition uh, I feel the franchise, franchisor support system is excellent.",
    "Start": "1:31",
    "End": "1:37"
  },
  {
    "Who": "Hamo Gharibian",
    "Word Count": 117,
    "Quote": "It's rewarding because ah, at the end of the day you're building something for your business. Something for yourself.",
    "Start": "1:37",
    "End": "1:44"
  },
  {
    "Who": "Joy Batchelor",
    "Word Count": 27,
    "Quote": "This is a no brainer to us.",
    "Start": "1:44",
    "End": "1:47"
  },
  {
    "Who": "Laura Griffin",
    "Word Count": 30,
    "Quote": "It has really changed my life.",
    "Start": "1:47",
    "End": "1:50"
  }
]